qiskit_qutree_cloud_provider/__init__.py
qiskit_qutree_cloud_provider/_version.py
qiskit_qutree_cloud_provider/backend.py
qiskit_qutree_cloud_provider/job.py
qiskit_qutree_cloud_provider/portfolio.py
qiskit_qutree_cloud_provider/algorithms/__init__.py
qiskit_qutree_cloud_provider/algorithms/minimum_eigensolvers/__init__.py
qiskit_qutree_cloud_provider/algorithms/minimum_eigensolvers/qaoa.py
qiskit_qutree_cloud_provider/algorithms/minimum_eigensolvers/vqe.py
qiskit_qutree_cloud_provider/primitives/__init__.py
qiskit_qutree_cloud_provider/primitives/qutree_estimator.py
qiskit_qutree_cloud_provider/rpc/__init__.py
qiskit_qutree_cloud_provider/rpc/qutree_pb2.py
qiskit_qutree_cloud_provider/rpc/qutree_pb2_grpc.py
qiskit_qutree_cloud_provider-0.4.1.dist-info/METADATA
qiskit_qutree_cloud_provider-0.4.1.dist-info/WHEEL
qiskit_qutree_cloud_provider-0.4.1.dist-info/top_level.txt
qiskit_qutree_cloud_provider-0.4.1.dist-info/RECORD
